jk_terminal_essentials/Spinner.py
jk_terminal_essentials/_TerminalSizeHelper.py
jk_terminal_essentials/__init__.py
jk_terminal_essentials/constants.py
jk_terminal_essentials/functions.py
jk_terminal_essentials-0.2024.2.2.dist-info/WHEEL
jk_terminal_essentials-0.2024.2.2.dist-info/METADATA
jk_terminal_essentials-0.2024.2.2.dist-info/RECORD
