Metadata-Version: 2.1
Name: jk_terminal_essentials
Version: 0.2024.2.2
Summary: This module provides essential constants and information about the terminal. This module is intended for implementing CLI tools and other applications running in a terminal.
Keywords: console,terminal,colors
Author-email: Jürgen Knauth <pubsrc@binary-overflow.de>
Maintainer-email: Jürgen Knauth <pubsrc@binary-overflow.de>
Requires-Python: >=3.8
Classifier: Development Status :: 5 - Production/Stable
Classifier: License :: OSI Approved :: Apache Software License
Classifier: Programming Language :: Python :: 3
